high_vision/__init__.py
high_vision/Detection/__init__.py
high_vision/Detection/yolov4/__init__.py
high_vision/Detection/yolov4/common/__init__.py
high_vision/Detection/yolov4/common/base_class.py
high_vision/Detection/yolov4/common/media.py
high_vision/Detection/yolov4/common/predict.py
high_vision/Detection/yolov4/model/__init__.py
high_vision/Detection/yolov4/model/backbone.py
high_vision/Detection/yolov4/model/common.py
high_vision/Detection/yolov4/model/head.py
high_vision/Detection/yolov4/model/neck.py
high_vision/Detection/yolov4/model/yolov4.py
high_vision/Detection/yolov4/tf/__init__.py
high_vision/Detection/yolov4/tf/dataset.py
high_vision/Detection/yolov4/tf/train.py
high_vision/Detection/yolov4/tf/utils.py
high_vision/Detection/yolov4/tf/weights.py
high_vision/Estimation/__init__.py
high_vision/Segmentation/__init__.py
high_vision/Segmentation/cdcl/__init__.py
high_vision/Segmentation/cdcl/config
high_vision/Segmentation/cdcl/config_reader.py
high_vision/Segmentation/cdcl/inference_15parts.py
high_vision/Segmentation/cdcl/inference_15parts_skeletons.py
high_vision/Segmentation/cdcl/model_simulated_RGB101.py
high_vision/Segmentation/cdcl/util.py
high_vision/Segmentation/cdcl/human_seg/__init__.py
high_vision/Segmentation/cdcl/human_seg/coco_human_seg_gt.py
high_vision/Segmentation/cdcl/human_seg/flood_fill.py
high_vision/Segmentation/cdcl/human_seg/human_seg_gt.py
high_vision/Segmentation/cdcl/mylayers/__init__.py
high_vision/Segmentation/cdcl/mylayers/__misc.py
high_vision/Segmentation/deeplab/__init__.py
high_vision/Segmentation/deeplab/deeplab.py
high_vision/Segmentation/deeplab/semantic.py
high_vision/Segmentation/maskrcnn/__init__.py
high_vision/Segmentation/maskrcnn/config.py
high_vision/Segmentation/maskrcnn/custom_train.py
high_vision/Segmentation/maskrcnn/instance.py
high_vision/Segmentation/maskrcnn/mask_rcnn.py
high_vision/Segmentation/maskrcnn/tune_bg.py
high_vision/Segmentation/maskrcnn/utils.py
high_vision-0.1.dist-info/METADATA
high_vision-0.1.dist-info/WHEEL
high_vision-0.1.dist-info/top_level.txt
high_vision-0.1.dist-info/RECORD
